MANIFEST.in
README
setup.py
funmap/__init__.py
funmap/test/__init__.py
funmap/test/test_funmap.py
horetu/__init__.py
horetu/exceptions.py
horetu/lib.py
horetu/signature.py
horetu/templates.py
horetu/util.py
horetu.egg-info/PKG-INFO
horetu.egg-info/SOURCES.txt
horetu.egg-info/dependency_links.txt
horetu.egg-info/requires.txt
horetu.egg-info/top_level.txt
horetu/input/__init__.py
horetu/input/_cli.py
horetu/input/_wsgi.py
horetu/input/lib.py
horetu/input/types.py
horetu/input/test/__init__.py
horetu/input/test/test_cli.py
horetu/input/test/test_lib.py
horetu/input/test/test_wsgi.py
horetu/output/__init__.py
horetu/output/defaults.py
horetu/output/test/__init__.py
horetu/output/test/test_.py
horetu/output/test/test_defaults.py
horetu/render/__init__.py
horetu/render/cli.py
horetu/render/doc.py
horetu/render/util.py
horetu/render/wsgi.py
horetu/render/templates/cli-man.txt
horetu/render/templates/cli-usage.txt
horetu/render/templates/config.txt
horetu/render/templates/wsgi-man.html
horetu/render/templates/wsgi-usage.html
horetu/render/templates/wsgi-usage.txt
horetu/render/test/__init__.py
horetu/render/test/test_doc.py
horetu/test/__init__.py
horetu/test/test_cli.py
horetu/test/test_examples.py
horetu/test/test_signature.py
horetu/test/test_util.py
triedict/__init__.py
triedict/test_.py