Metadata-Version: 1.1
Name: horetu
Version: 0.2.3
Summary: Make a command-line interface from a function.
Home-page: http://src.thomaslevine.com/horetu/
Author: Thomas Levine
Author-email: _@thomaslevine.com
License: AGPL
Platform: UNKNOWN
Classifier: Programming Language :: Python :: 3.5
